agent_tools/__init__.py
agent_tools/_info.py
agent_tools/_log.py
agent_tools/agent_base.py
agent_tools/agent_factory.py
agent_tools/agent_runner.py
agent_tools/agent_switcher.py
agent_tools/ark_agent.py
agent_tools/azure_agent.py
agent_tools/bailian_agent.py
agent_tools/credential_pool_base.py
agent_tools/laozhang_agent.py
agent_tools/model_relay_agent.py
agent_tools/openai_agent.py
agent_tools/openai_ft_agent.py
agent_tools/openai_pools_agent.py
agent_tools/provider_config.py
agent_tools/provider_registry.py
agent_tools/py.typed
agent_tools/settings.py
agent_tools/tools4test.py
agent_tools/vertex_agent.py
agent_tools/wechat_alert.py
py_agent_tools-0.1.8.post17.dist-info/METADATA
py_agent_tools-0.1.8.post17.dist-info/WHEEL
py_agent_tools-0.1.8.post17.dist-info/top_level.txt
py_agent_tools-0.1.8.post17.dist-info/RECORD
