Metadata-Version: 2.4
Name: py-agent-tools
Version: 0.1.8.post17
Summary: Agent Switcher
Author-email: Sheldon Lee <sheldonlee@outlook.com>
Project-URL: Homepage, https://github.com/sheldonldev/py-agent-tools
Project-URL: Repository, https://github.com/sheldonldev/py-agent-tools
Project-URL: Issues, https://github.com/sheldonldev/py-agent-tools/issues
Classifier: Programming Language :: Python :: 3
Classifier: Operating System :: OS Independent
Requires-Python: >=3.10
Provides-Extra: dev
Requires-Dist: pip; extra == "dev"
Requires-Dist: twine; extra == "dev"
Requires-Dist: build; extra == "dev"
Requires-Dist: mypy; extra == "dev"
Requires-Dist: pre-commit; extra == "dev"
